contextwormhole/__init__.py
contextwormhole/cli.py
contextwormhole/contextwormhole.py
contextwormhole/core.py
contextwormhole-1.2.0.dist-info/licenses/LICENSE
contextwormhole-1.2.0.dist-info/METADATA
contextwormhole-1.2.0.dist-info/WHEEL
contextwormhole-1.2.0.dist-info/entry_points.txt
contextwormhole-1.2.0.dist-info/top_level.txt
contextwormhole-1.2.0.dist-info/RECORD
