Metadata-Version: 2.4
Name: contextwormhole
Version: 1.2.0
Summary: Teleport beyond context limits with transformers
Home-page: https://github.com/contextwormhole/contextwormhole
Author: ContextWormhole Team
Author-email: ContextWormhole Team <team@contextwormhole.dev>
License-Expression: MIT
Project-URL: Bug Reports, https://github.com/contextwormhole/contextwormhole/issues
Project-URL: Source, https://github.com/contextwormhole/contextwormhole
Project-URL: Documentation, https://contextwormhole.readthedocs.io/
Keywords: transformers,nlp,context,attention,huggingface,pytorch
Classifier: Development Status :: 4 - Beta
Classifier: Intended Audience :: Developers
Classifier: Intended Audience :: Science/Research
Classifier: Operating System :: OS Independent
Classifier: Programming Language :: Python :: 3
Classifier: Programming Language :: Python :: 3.8
Classifier: Programming Language :: Python :: 3.9
Classifier: Programming Language :: Python :: 3.10
Classifier: Programming Language :: Python :: 3.11
Classifier: Topic :: Scientific/Engineering :: Artificial Intelligence
Classifier: Topic :: Software Development :: Libraries :: Python Modules
Requires-Python: >=3.8
License-File: LICENSE
Requires-Dist: torch>=1.9.0
Requires-Dist: transformers>=4.20.0
Requires-Dist: numpy<2.0.0,>=1.20.0
Provides-Extra: dev
Requires-Dist: pytest>=7.0.0; extra == "dev"
Requires-Dist: pytest-cov>=3.0.0; extra == "dev"
Requires-Dist: pytest-mock>=3.6.0; extra == "dev"
Requires-Dist: pytest-benchmark>=3.4.0; extra == "dev"
Provides-Extra: docs
Requires-Dist: sphinx>=4.0.0; extra == "docs"
Requires-Dist: sphinx-rtd-theme>=1.0.0; extra == "docs"
Requires-Dist: myst-parser>=0.18.0; extra == "docs"
Provides-Extra: lint
Requires-Dist: black>=22.0.0; extra == "lint"
Requires-Dist: flake8>=4.0.0; extra == "lint"
Requires-Dist: isort>=5.10.0; extra == "lint"
Requires-Dist: mypy>=0.910; extra == "lint"
Provides-Extra: all
Requires-Dist: pytest>=7.0.0; extra == "all"
Requires-Dist: pytest-cov>=3.0.0; extra == "all"
Requires-Dist: pytest-mock>=3.6.0; extra == "all"
Requires-Dist: pytest-benchmark>=3.4.0; extra == "all"
Requires-Dist: sphinx>=4.0.0; extra == "all"
Requires-Dist: sphinx-rtd-theme>=1.0.0; extra == "all"
Requires-Dist: myst-parser>=0.18.0; extra == "all"
Requires-Dist: black>=22.0.0; extra == "all"
Requires-Dist: flake8>=4.0.0; extra == "all"
Requires-Dist: isort>=5.10.0; extra == "all"
Requires-Dist: mypy>=0.910; extra == "all"
Dynamic: author
Dynamic: home-page
Dynamic: license-file
Dynamic: project-url
Dynamic: provides-extra
Dynamic: requires-python
